OpenChatGPT/__init__.py
OpenChatGPT/openai_chat.py
OpenChatGPT-0.11.dist-info/METADATA
OpenChatGPT-0.11.dist-info/WHEEL
OpenChatGPT-0.11.dist-info/top_level.txt
OpenChatGPT-0.11.dist-info/RECORD
